{
  "$schema": "http://schemas.microsoft.org/azure/deploymentTemplate?api-version=2015-01-01-preview#",
  "contentVersion": "1.0",
  "parameters": {
    "accountName": {
      "type": "string",
      "metadata": {
        "description": "The name of the Azure Automation account to deploy to."
      }
    },
    "regionId": {
      "type": "string",
      "allowedValues": [
        "Japan East",
        "East US 2",
        "West Europe",
        "Southeast Asia",
        "South Central US"
      ],
      "metadata": {
        "description": "The region to deploy the Automation account in."
      }
    },
    "pricingTier": {
      "type": "string",
      "allowedValues": ["Free", "Basic"],
      "metadata": {
        "description": "The pricing tier for the account."
      }
    },
    "credentialName": {
      "type": "string",
      "metadata": {
        "description": "The name of the credential to deploy."
      }
    },
    "userName": {
      "type": "string",
      "metadata": {
        "description": "The username for the Azure Automation credential."
      }
    },
    "password": {
      "type": "secureString",
      "metadata": {
        "description": "The password for the Azure Automation credential."
      }
    }
  },
  "variables": {},
  "resources": [
    {
      "name": "[parameters('accountName')]",
      "type": "Microsoft.Automation/automationAccounts",
      "apiVersion": "2015-01-01-preview",
      "location": "[parameters('regionId')]",
      "dependsOn": [],
      "tags": {},
      "properties": {
        "sku": {
          "name": "[parameters('pricingTier')]"
        }
      },
      "resources": [
        {
          "name": "[parameters('credentialName')]",
          "type": "credentials",
          "apiVersion": "2015-01-01-preview",
          "location": "[parameters('regionId')]",
          "dependsOn": [
            "[concat('Microsoft.Automation/automationAccounts/', parameters('accountName'))]"
          ],
          "tags": {},
          "properties": {
            "userName": "[parameters('userName')]",
            "password": "[parameters('password')]"
          }
        }
      ]
    }
  ],
  "outputs": {}
}
